README.md
setup.py
maximus48/FSC.py
maximus48/FSC2.py
maximus48/SSIM_131119.py
maximus48/__init__.py
maximus48/monochromaticCTF.py
maximus48/multiCTF2.py
maximus48/polar.py
maximus48/polar2.py
maximus48/sidi_phare.py
maximus48/tomo_proc3.py
maximus48/var.py
maximus48.egg-info/.DS_Store
maximus48.egg-info/PKG-INFO
maximus48.egg-info/SOURCES.txt
maximus48.egg-info/dependency_links.txt
maximus48.egg-info/top_level.txt