Metadata-Version: 1.0
Name: maximus48
Version: 1.2.1
Summary: Useful tools for image processing & parallel-beam X-ray tomography
Home-page: https://github.com/maximka48/maximus48
Author: Maxim Polikarpov
Author-email: polikarpov.maxim@mail.ru
License: MIT License
Keywords: tomography,reconstruction,imaging
Platform: OS Independent
